{"cameraMode":{"drawMode":0,"name":"Shaded","section":"Shading Mode"},"sceneLighting":true,"audioPlay":false,"sceneViewState":{"showFog":true,"showMaterialUpdate":false,"showSkybox":true,"showFlares":true,"showImageEffects":true,"showParticleSystems":true},"in2DMode":false,"pivot":{"x":-0.09909431636333466,"y":0.37771543860435488,"z":0.27290230989456179},"rotation":{"x":-0.04789070412516594,"y":0.9509291648864746,"z":-0.23907746374607087,"w":-0.19048534333705903},"size":1.4332702159881592,"orthographic":false}